<item>
   <title>Issue #816 created</title>
   <pubDate>2023-11-06T15:43:36Z</pubDate>
   <link>https://github.com/qt4cg/qtspecs/issues/816</link>
   <guid>https://qt4cg.org/@qt4cg/2023/#created-816</guid>
   <description>&lt;div&gt;&lt;p&gt;Predicates: Support for numeric sequences &lt;/p&gt;&lt;div class="markup"&gt;&lt;p&gt;Predicates provide a compact syntax for positional access to sequences but only single numbers are supported.&lt;/p&gt;
&lt;p&gt;It would be handy to allow &lt;code&gt;E[1, 2, 3]&lt;/code&gt; (&lt;code&gt;E[3, 2, 1]&lt;/code&gt;, &lt;code&gt;E[1 to 3]&lt;/code&gt;, etc.) as a shortcut for &lt;code&gt;E[position() = (1, 2, 3)]&lt;/code&gt; (MarkLogic offers this possibility, if I remember correctly). We shouldn’t change the EBV syntax, and we should continue raising an error  if the predicate sequence contains items other than numbers. Examples:&lt;/p&gt;
&lt;p&gt;Expression | Result
--- | ---
&lt;code&gt;(1 to 5)[2, 3]&lt;/code&gt; | &lt;code&gt;2, 3&lt;/code&gt;
&lt;code&gt;(1 to 5)[3, 2]&lt;/code&gt; | &lt;code&gt;2, 3&lt;/code&gt;
&lt;code&gt;(1 to 5)[2 to 3]&lt;/code&gt; | &lt;code&gt;2, 3&lt;/code&gt;
&lt;code&gt;(1 to 5)[6, 'x']&lt;/code&gt; | &lt;em&gt;error&lt;/em&gt;
&lt;code&gt;(1 to 5)[1 to 5, 'x']&lt;/code&gt; | &lt;code&gt;1, 2, 3, 4, 5&lt;/code&gt; or &lt;em&gt;error&lt;/em&gt; (up to the implementation, similar to sequences that start with a node)&lt;/p&gt;
&lt;p&gt;I bet this has already been discussed in the past…&lt;/p&gt;
&lt;/div&gt;&lt;/div&gt;</description>
</item>
