{"stem":"1459","instances":[{"docUri":"2026\/02-17.html","score":4,"contexts":[{"form":"1459","weight":"2","pos":1230,"context":"2.3.12. <mark>1459<\/mark> Function properties and arities","fid":"issue-1459"},{"form":"1459","weight":"1","pos":164,"context":"2.3.12. <mark>1459<\/mark> Function properties and arities","fid":"text-table-of-contents"},{"form":"1459","weight":"1","pos":1235,"context":" See #<mark>1459<\/mark> ","fid":"text-issue-1459"}]},{"docUri":"2025\/04-22.html","score":1,"contexts":[{"form":"1459","weight":"1","pos":1023,"context":"Issue #<mark>1459<\/mark>: Function properties and arities (editorial)","fid":"text-triage"}]}]}