{"stem":"bigger","instances":[{"docUri":"2024\/10-01.html","score":1,"contexts":[{"form":"bigger","weight":"1","pos":737,"context":"…that there are built in record types is a <mark>bigger<\/mark> step that I think is not necessarily required.…","fid":"text-pr-1465"}]},{"docUri":"2024\/07-16.html","score":1,"contexts":[{"form":"bigger","weight":"1","pos":511,"context":"I think there are <mark>bigger<\/mark> communication problems:","fid":"text-communication"}]},{"docUri":"2024\/03-19.html","score":1,"contexts":[{"form":"bigger","weight":"1","pos":1038,"context":"…if we can step back. Are there any <mark>bigger<\/mark> issues?","fid":"text-pr-1066"}]},{"docUri":"2026\/06-02.html","score":1,"contexts":[{"form":"bigger","weight":"1","pos":2128,"context":"…The demand for streaming is down (because hardware is <mark>bigger<\/mark>), but the 2^31 limit on Java and…","fid":"text-iss-675"}]},{"docUri":"2026\/06-16.html","score":1,"contexts":[{"form":"bigger","weight":"1","pos":953,"context":"…version. The diff makes it looks like a <mark>bigger<\/mark> change than it is.","fid":"text-pr-2678"}]}]}