{"stem":"catalog","instances":[{"docUri":"2023\/01-17.html","score":2,"contexts":[{"form":"catalog","weight":"1","pos":852,"context":"Fix validity issues with the function <mark>catalog<\/mark> and its schema (Issue 291)","fid":"text-h-6142CC30-B435-4A23-8FEB-C7C5DAA040DD"},{"form":"catalog","weight":"1","pos":867,"context":"Extend the function <mark>catalog<\/mark> to handle record definitions (Issue 257)","fid":"text-h-6142CC30-B435-4A23-8FEB-C7C5DAA040DD"}]},{"docUri":"2026\/01-20.html","score":3,"contexts":[{"form":"catalogs","weight":"2","pos":956,"context":"…#2379: Use exported schema to validate function <mark>catalogs<\/mark>","fid":"pr-2379"},{"form":"catalogs","weight":"1","pos":115,"context":"…#2379: Use exported schema to validate function <mark>catalogs<\/mark>","fid":"text-table-of-contents"}]},{"docUri":"2026\/02-17.html","score":2,"contexts":[{"form":"catalog","weight":"1","pos":815,"context":"…a schema change to allow results in the function <mark>catalog<\/mark> to be annotated as narrative. A narrative result…","fid":"text-h-F7DE29C3-E195-4196-9A09-81D2E5F578E1"},{"form":"catalog","weight":"1","pos":844,"context":"…makes use of that markup in the F&amp;O function <mark>catalog<\/mark>.","fid":"text-h-F7DE29C3-E195-4196-9A09-81D2E5F578E1"}]},{"docUri":"2025\/02-04.html","score":1,"contexts":[{"form":"catalogs","weight":"1","pos":640,"context":"…: Fix validation issues in the EXPath module function <mark>catalogs<\/mark>","fid":"text-merge-without-discussion"}]},{"docUri":"2024\/11-26.html","score":1,"contexts":[{"form":"catalog","weight":"1","pos":566,"context":"…: 1590 Drop draft current-mode function from <mark>catalog<\/mark>","fid":"text-merge-without-discussion"}]},{"docUri":"2023\/06-20.html","score":1,"contexts":[{"form":"catalog","weight":"1","pos":604,"context":"The RFC is an attempt to <mark>catalog<\/mark> existing practice. It was rather Anglo-centric…","fid":"text-parse-csv"}]},{"docUri":"2023\/11-28.html","score":1,"contexts":[{"form":"catalog","weight":"1","pos":597,"context":"… Uses a pre-defined <mark>catalog<\/mark> of shortname to URI mappings.","fid":"text-pr-470"}]}]}