{"stem":"caught","instances":[{"docUri":"2022\/11-15.html","score":2,"contexts":[{"form":"caught","weight":"1","pos":747,"context":"…new text uses the unqualified term “function” and it <mark>caught<\/mark> my eye partly because early on in this pull…","fid":"text-pr-variadic-functions"},{"form":"caught","weight":"1","pos":808,"context":"…MSM: I’m pretty sure that the bit that <mark>caught<\/mark> my eye was “apropos of lookup” where there’s a…","fid":"text-pr-variadic-functions"}]},{"docUri":"2025\/01-07.html","score":1,"contexts":[{"form":"caught","weight":"1","pos":934,"context":"…as UTF-16 code unit collation. That’s <mark>caught<\/mark> me out more than once!","fid":"text-pr-1676"}]}]}