{"stem":"communic","instances":[{"docUri":"2024\/07-16.html","score":12,"contexts":[{"form":"communication","weight":"2","pos":369,"context":"2.1. Community, <mark>communication<\/mark>, and consensus","fid":"communication"},{"form":"communication","weight":"1","pos":57,"context":"2.1. Community, <mark>communication<\/mark>, and consensus","fid":"text-table-of-contents"},{"form":"communication","weight":"1","pos":504,"context":"…by the facts. I agree that we have <mark>communication<\/mark> issues. And our communication will be reflected in…","fid":"text-communication"},{"form":"communication","weight":"1","pos":506,"context":"…agree that we have communication issues. And our <mark>communication<\/mark> will be reflected in the final project.  ","fid":"text-communication"},{"form":"communication","weight":"1","pos":512,"context":"I think there are bigger <mark>communication<\/mark> problems:","fid":"text-communication"},{"form":"communication","weight":"1","pos":555,"context":"…no one has noticed. We have problems in <mark>communication<\/mark> and approval of PRs.","fid":"text-communication"},{"form":"communication","weight":"1","pos":594,"context":"…shows much deeper and more serious issues in our <mark>communication<\/mark>.","fid":"text-communication"},{"form":"communication","weight":"1","pos":836,"context":"…with MK. It’s good that we’re talking about <mark>communication<\/mark> problems, but if we’re only talking it’s not…","fid":"text-communication"},{"form":"communication","weight":"1","pos":929,"context":"…was right that we’ve drifted from the question of <mark>communication<\/mark> style and interaction to questions of quality assurance.…","fid":"text-communication"},{"form":"communication","weight":"1","pos":951,"context":"…agitated and push the boundaries of normal rules of <mark>communication<\/mark>. I think we’ve had some suggestions for improved…","fid":"text-communication"},{"form":"communication","weight":"1","pos":961,"context":"…I would like to make some suggestions for improved <mark>communication<\/mark>:      ","fid":"text-communication"}]},{"docUri":"2026\/01-20.html","score":1,"contexts":[{"form":"Communications","weight":"1","pos":972,"context":"…Update from JLO about teaching XSLT at the CHAOS <mark>Communications<\/mark> Congress. ","fid":"text-any-other-business"}]},{"docUri":"2026\/03-17.html","score":1,"contexts":[{"form":"communicate","weight":"1","pos":1013,"context":"…all implementation details. Who are we trying to <mark>communicate<\/mark> with in the spec?","fid":"text-pr-2516"}]}]}