{"stem":"debug","instances":[{"docUri":"2023\/10-31.html","score":3,"contexts":[{"form":"debug","weight":"1","pos":828,"context":"…has the best context. Are you trying to <mark>debug<\/mark> the processor or the program? Most of the…","fid":"text-iss-689"},{"form":"debugging","weight":"1","pos":832,"context":"…processor or the program? Most of the folks <mark>debugging<\/mark> a processor are probably in this room. There…","fid":"text-iss-689"},{"form":"debug","weight":"1","pos":839,"context":"…. There are a lot more users trying to <mark>debug<\/mark> their programs. Optimization makes the stack traces just…","fid":"text-iss-689"}]},{"docUri":"2025\/06-24.html","score":2,"contexts":[{"form":"debugging","weight":"1","pos":774,"context":"…CG: The adative serialization method is mostly for <mark>debugging<\/mark>, so we can make that simpler.","fid":"text-qname-literals"},{"form":"debugging","weight":"1","pos":827,"context":"JWL: If this is really for <mark>debugging<\/mark> and you aren’t going to parse it, I’m not…","fid":"text-qname-literals"}]},{"docUri":"2025\/03-25.html","score":1,"contexts":[{"form":"debug","weight":"1","pos":762,"context":"…extremely wrong and makes logical errors very difficult to <mark>debug<\/mark>.","fid":"text-pr-1766"}]},{"docUri":"2025\/10-07.html","score":1,"contexts":[{"form":"debugging","weight":"1","pos":651,"context":"Issue #1153: XSLT: <mark>debugging<\/mark> template rule selection","fid":"text-close-without-action"}]},{"docUri":"2025\/12-16.html","score":1,"contexts":[{"form":"debugging","weight":"1","pos":1212,"context":"… Tracing and <mark>debugging<\/mark>, that are entirely conformant, and other things…","fid":"text-pr-2283"}]},{"docUri":"2025\/04-22.html","score":1,"contexts":[{"form":"debugging","weight":"1","pos":1502,"context":"…correct that this function would be used mainly while <mark>debugging<\/mark>?","fid":"text-pr-1933"}]},{"docUri":"2025\/09-23.html","score":1,"contexts":[{"form":"debug","weight":"1","pos":813,"context":"…could introduce a new weakness where it’s hard to <mark>debug<\/mark>.","fid":"text-pr-2200"}]},{"docUri":"2024\/01-30.html","score":1,"contexts":[{"form":"debugging","weight":"1","pos":879,"context":"…scan-right can be used as tracing\/<mark>debugging<\/mark> tools for people who are using fold-left…","fid":"text-pr-957"}]},{"docUri":"2024\/11-26.html","score":1,"contexts":[{"form":"debugging","weight":"1","pos":769,"context":"…in things like query result output, profiling, <mark>debugging<\/mark>, etc.","fid":"text-pr-1570"}]},{"docUri":"2024\/06-04.html","score":2,"contexts":[{"form":"debugging","weight":"2","pos":2962,"context":"2.2.103. 1153, XSLT: <mark>debugging<\/mark> template rule selection","fid":"iss-1153"}]},{"docUri":"2023\/01-31.html","score":1,"contexts":[{"form":"debug","weight":"1","pos":941,"context":"CG: Do we need the <mark>debug<\/mark> option if we have fn:differences?","fid":"text-h-8455483D-D0AF-499A-A74A-552B33A9F395"}]},{"docUri":"2023\/11-28.html","score":1,"contexts":[{"form":"debugging","weight":"1","pos":916,"context":"…overrides for example. But it makes testing and <mark>debugging<\/mark> terribly difficult. The xs:redefine mechanism introduces…","fid":"text-pr-470"}]}]}