{"stem":"number-format","instances":[{"docUri":"2026\/04-28.html","score":5,"contexts":[{"form":"number-format","weight":"2","pos":942,"context":"…2593: 2592 Change number-parser option to <mark>number-format<\/mark>","fid":"pr-2593"},{"form":"number-format","weight":"1","pos":114,"context":"…2593: 2592 Change number-parser option to <mark>number-format<\/mark>","fid":"text-table-of-contents"},{"form":"number-format","weight":"1","pos":551,"context":"…2593: 2592 Change number-parser option to <mark>number-format<\/mark>","fid":"text-substantive"},{"form":"number-format","weight":"1","pos":963,"context":"…the number-parser function and replace it with <mark>number-format<\/mark> that has three possible values.  ","fid":"text-pr-2593"}]},{"docUri":"2025\/10-21.html","score":1,"contexts":[{"form":"number-format","weight":"1","pos":713,"context":"…So are we thinking about something more like the <mark>number-format<\/mark> options?   ","fid":"text-pr-2223"}]}]}