{"stem":"we'd","instances":[{"docUri":"2025\/09-16.html","score":5,"contexts":[{"form":"we’d","weight":"1","pos":656,"context":"…fear that if we wanted to use QNames, <mark>we’d<\/mark> quickly have questions about how to use EQNames and…","fid":"text-pr-2171"},{"form":"we’d","weight":"1","pos":663,"context":"…about how to use EQNames and default prefixes and <mark>we’d<\/mark> be back where we started.","fid":"text-pr-2171"},{"form":"we’d","weight":"1","pos":1000,"context":"…think this was an accidental ommision. We thought <mark>we’d<\/mark> agreed to it, but when I looked at the…","fid":"text-pr-2182"},{"form":"we’d","weight":"1","pos":1004,"context":"…it, but when I looked at the spec, <mark>we’d<\/mark> added to the list of known namespaces, but…","fid":"text-pr-2182"},{"form":"we’d","weight":"1","pos":1180,"context":"…If it was deeper, I’m not sure if <mark>we’d<\/mark> get some nasty ambiguities.","fid":"text-pr-2181"}]},{"docUri":"2022\/09-20.html","score":3,"contexts":[{"form":"we’d","weight":"1","pos":989,"context":"…in place of the existing namespace functions, if <mark>we’d<\/mark> had maps from the start. I’ve reformulated the…","fid":"text-h-A0753EA6-25CF-4526-9DB3-4CC920B55ECD"},{"form":"we’d","weight":"1","pos":1317,"context":"RD: I think <mark>we’d<\/mark> need a separate proposal for that function.","fid":"text-h-F050FE3C-2F4B-424C-90BA-DF7ECCFB268E"},{"form":"We’d","weight":"1","pos":1688,"context":"MK: <mark>We’d<\/mark> require more flexibility with arities and what function coerction…","fid":"text-h-42CFD76B-1E1C-4B38-8A1E-A9DD3A0094D9"}]},{"docUri":"2022\/09-13.html","score":2,"contexts":[{"form":"we’d","weight":"1","pos":1155,"context":"…rules. The spec is in the rule, <mark>we’d<\/mark> just have to wrap it in function and we’d…","fid":"text-2-1-2"},{"form":"we’d","weight":"1","pos":1158,"context":"…we’d just have to wrap it in function and <mark>we’d<\/mark> be done.","fid":"text-2-1-2"}]},{"docUri":"2024\/12-10.html","score":2,"contexts":[{"form":"We’d","weight":"1","pos":1163,"context":"…related, so I tried to tackle them both. <mark>We’d<\/mark> extend the data model to provide a property for…","fid":"text-pr-1609"},{"form":"we’d","weight":"1","pos":1555,"context":"MK: I’m nervous about whether <mark>we’d<\/mark> be imposing a performance cost on users who don’t…","fid":"text-pr-1609"}]},{"docUri":"2024\/06-04.html","score":2,"contexts":[{"form":"we’d","weight":"1","pos":2500,"context":"NW: MK is right that <mark>we’d<\/mark> need fn:uuid-generator …","fid":"text-iss-885"},{"form":"we’d","weight":"1","pos":4222,"context":"… There have been lots of suggestions that <mark>we’d<\/mark> like the names of the parameters to be a…","fid":"text-variable-arity-dynamic-functions"}]},{"docUri":"2023\/05-23.html","score":2,"contexts":[{"form":"We’d","weight":"1","pos":974,"context":"… <mark>We’d<\/mark> need to fudge a bit; you’d have to…","fid":"text-iss-414"},{"form":"we’d","weight":"1","pos":1405,"context":" Some discussion of what <mark>we’d<\/mark> need. Read-binary and conversion functions,…","fid":"text-iss-414"}]},{"docUri":"2023\/10-31.html","score":2,"contexts":[{"form":"we’d","weight":"1","pos":981,"context":"…useful. If we implemented stack tracing, then <mark>we’d<\/mark> want to suppress some optimizations. That would mean…","fid":"text-iss-689"},{"form":"we’d","weight":"1","pos":997,"context":"…very likely hide the error! I’m not sure <mark>we’d<\/mark> meet user expectations.","fid":"text-iss-689"}]},{"docUri":"2022\/10-18.html","score":1,"contexts":[{"form":"we’d","weight":"1","pos":727,"context":"…that we can’t reference keys with spaces? So <mark>we’d<\/mark> need to support stings. If we only support…","fid":"text-issue-165"}]},{"docUri":"2022\/12-06.html","score":1,"contexts":[{"form":"we’d","weight":"1","pos":993,"context":" I think <mark>we’d<\/mark> be helping the QT community if we made that…","fid":"text-iss-274"}]},{"docUri":"2022\/11-22.html","score":1,"contexts":[{"form":"we’d","weight":"1","pos":1397,"context":"…with the hash symbol and a number. Then <mark>we’d<\/mark> get linking from PRs to issues and commits.…","fid":"text-any-other-business"}]},{"docUri":"2025\/05-27.html","score":1,"contexts":[{"form":"we’d","weight":"1","pos":1039,"context":"… There’s a field <mark>we’d<\/mark> like to make private, but we can’t,…","fid":"text-pr-1959"}]},{"docUri":"2025\/01-28.html","score":1,"contexts":[{"form":"we’d","weight":"1","pos":1136,"context":"…make the publication coherent, as distinct from what <mark>we’d<\/mark> like to do. We should focus on resolving the…","fid":"text-turningtheship"}]},{"docUri":"2025\/07-22.html","score":1,"contexts":[{"form":"We’d","weight":"1","pos":1201,"context":"MK: <mark>We’d<\/mark> have to refine the rules about reserved function names…","fid":"text-pr-2071"}]},{"docUri":"2025\/11-11.html","score":1,"contexts":[{"form":"We’d","weight":"1","pos":842,"context":"… <mark>We’d<\/mark> probably do that differently if we were adding it…","fid":"text-pr-2266"}]},{"docUri":"2025\/08-19.html","score":1,"contexts":[{"form":"we’d","weight":"1","pos":626,"context":"MK: The history of this is that <mark>we’d<\/mark> changed the eq operator to allow mutual comparisons.…","fid":"text-pr-2168"}]},{"docUri":"2025\/11-18.html","score":1,"contexts":[{"form":"we’d","weight":"1","pos":1426,"context":"…… And I can still see CG’s argument that <mark>we’d<\/mark> like it to be simple.","fid":"text-pr-2282"}]},{"docUri":"2025\/07-29.html","score":1,"contexts":[{"form":"we’d","weight":"1","pos":911,"context":"CG: So <mark>we’d<\/mark> get &lt;a1\/&gt; for the first case.  ","fid":"text-pr-2116"}]},{"docUri":"2025\/09-30.html","score":1,"contexts":[{"form":"we’d","weight":"1","pos":869,"context":"…and advanced grouping in XSLT? I’m not sure <mark>we’d<\/mark> have a good answer.","fid":"text-pr-2123"}]},{"docUri":"2025\/02-04.html","score":1,"contexts":[{"form":"we’d","weight":"1","pos":936,"context":"…-close, this is an optional feature that <mark>we’d<\/mark> like to have, but we’re going to abandon it…","fid":"text-issue-triage"}]},{"docUri":"2025\/03-18.html","score":1,"contexts":[{"form":"We’d","weight":"1","pos":1327,"context":"… <mark>We’d<\/mark> need an implementor.","fid":"text-any-other-business"}]},{"docUri":"2025\/03-11.html","score":1,"contexts":[{"form":"we’d","weight":"1","pos":659,"context":"…intuitive use case for scan-right. And <mark>we’d<\/mark> need to add the array equivalents as well.…","fid":"text-pr-1735"}]},{"docUri":"2025\/02-18.html","score":1,"contexts":[{"form":"we’d","weight":"1","pos":1158,"context":"…look at the proposal, it looks as if <mark>we’d<\/mark> be changing the behavior of array:get and…","fid":"text-pr-1766"}]},{"docUri":"2024\/09-10.html","score":1,"contexts":[{"form":"we’d","weight":"1","pos":875,"context":"…If we wanted to use the ⏵ character, <mark>we’d<\/mark> have to address those problems.  ","fid":"text-issue-755"}]},{"docUri":"2024\/07-09.html","score":1,"contexts":[{"form":"we’d","weight":"1","pos":513,"context":"MK: Maybe, but <mark>we’d<\/mark> be in danger of repeating ourselves.","fid":"text-pr-1313"}]},{"docUri":"2024\/02-13.html","score":1,"contexts":[{"form":"we’d","weight":"1","pos":1090,"context":"…concept to other items in general. And then <mark>we’d<\/mark> have a unified mechanism for associating this kind of…","fid":"text-pr-988"}]},{"docUri":"2024\/07-16.html","score":1,"contexts":[{"form":"we’d","weight":"1","pos":1214,"context":"…based on the syntax of the match patterns, <mark>we’d<\/mark> immediately be incompatible with 3.0.  ","fid":"text-pr-1263"}]},{"docUri":"2024\/11-26.html","score":1,"contexts":[{"form":"we’d","weight":"1","pos":1228,"context":"…the record type map-pair, I think <mark>we’d<\/mark> have enough context for it.","fid":"text-pr-1586"}]},{"docUri":"2023\/07-25.html","score":1,"contexts":[{"form":"we’d","weight":"1","pos":694,"context":"MK: Do we know how <mark>we’d<\/mark> use this?","fid":"text-h-9C3A29A5-7411-4C95-A8CB-0A0FF80A1402"}]},{"docUri":"2023\/02-21.html","score":1,"contexts":[{"form":"we’d","weight":"1","pos":591,"context":"MK: If we wanted to go further, <mark>we’d<\/mark> start by looking at third party vocabularies.","fid":"text-h-3C80588B-6B82-4EC0-95FE-7756A2EC5DCB"}]},{"docUri":"2023\/06-13.html","score":1,"contexts":[{"form":"we’d","weight":"1","pos":720,"context":"…something. We should propose specific features or proposals <mark>we’d<\/mark> like to see in the next version. Maybe…","fid":"text-new-labels"}]},{"docUri":"2023\/03-14.html","score":1,"contexts":[{"form":"We’d","weight":"1","pos":652,"context":"…that’s what it would be if we allowed it. <mark>We’d<\/mark> just be saying that we didn’t require at least…","fid":"text-h-29A87C61-D673-4C02-AF2C-DC56FD7B0F9F"}]},{"docUri":"2023\/02-14.html","score":1,"contexts":[{"form":"We’d","weight":"1","pos":1367,"context":"MK: <mark>We’d<\/mark> need a new option if we wanted to change…","fid":"text-h-8455483D-D0AF-499A-A74A-552B33A9F395"}]},{"docUri":"2023\/04-04.html","score":1,"contexts":[{"form":"We’d","weight":"1","pos":792,"context":"RD: <mark>We’d<\/mark> need to make something that was a “table of…","fid":"text-iss-399"}]},{"docUri":"2026\/01-27.html","score":1,"contexts":[{"form":"we’d","weight":"1","pos":869,"context":"… We have to draw a line and <mark>we’d<\/mark> still have a conherent spec without those things.…","fid":"text-h-7AB4E5D4-B0D5-4AB1-B2EF-E2CA108947C3"}]}]}