<item>
   <title>Pull request #1051 created</title>
   <pubDate>2024-02-28T23:58:33Z</pubDate>
   <link>https://github.com/qt4cg/qtspecs/pull/1051</link>
   <guid>https://qt4cg.org/@qt4cg/2024/#created-1051</guid>
   <description>&lt;div&gt;&lt;p&gt;1043 Clarification of CSV edge cases&lt;/p&gt;&lt;div class="markup"&gt;&lt;p&gt;Gives a more precise definition of blank rows and empty fields, and generally adds detail on how edge cases should be handled.&lt;/p&gt;
&lt;p&gt;Fix #1043.&lt;/p&gt;
&lt;/div&gt;&lt;/div&gt;</description>
</item>
