<item>
   <title>Issue #2475 created</title>
   <pubDate>2026-02-19T07:27:16Z</pubDate>
   <link>https://github.com/qt4cg/qtspecs/issues/2475</link>
   <guid>https://qt4cg.org/@qt4cg/2026/#created-2475</guid>
   <description>&lt;div&gt;&lt;p&gt;JNode types, node kind tests: Unifications&lt;/p&gt;&lt;div class="markup"&gt;&lt;p&gt;It’s always rewarding when syntax needs only to be learnt once, and I think the current &lt;code&gt;JNodeType&lt;/code&gt; and &lt;code&gt;NodeKindTest&lt;/code&gt; rules could be further aligned:&lt;/p&gt;
&lt;ul&gt;
&lt;li&gt;With the JNode type syntax, a wildcard can be used for the sequence type: &lt;code&gt;jnode(a, *)&lt;/code&gt;. We should either allow this for element (attribute, …) tests – for example, &lt;code&gt;element(name, *)&lt;/code&gt; – or we should discard &lt;code&gt;jnode(name, *)&lt;/code&gt; – &lt;code&gt;jnode(name)&lt;/code&gt; is equivalent.&lt;/li&gt;
&lt;li&gt;Similar as for element tests, we could allow unions in JNode types: &lt;code&gt;jnode(a|b|'c d')&lt;/code&gt;:&lt;/li&gt;
&lt;/ul&gt;
&lt;pre&gt;&lt;code&gt;JNodeType      ::=  'jnode' '(' ( JKeyTestUnion ( ',' JValueType )? )? ')'
JKeyTestUnion  ::=  JKeyTest ( '|' JKeyTest )*
JKeyTest       ::=  JRootSelector | NCName | Constant
JValueType     ::=  '*' | SequenceType
&lt;/code&gt;&lt;/pre&gt;
&lt;p&gt;Proposed renamings in the grammar:&lt;/p&gt;
&lt;ul&gt;
&lt;li&gt;&lt;code&gt;NodeKindTest&lt;/code&gt; → &lt;code&gt;XNodeType&lt;/code&gt;&lt;/li&gt;
&lt;li&gt;&lt;code&gt;DocumentTest&lt;/code&gt; → &lt;code&gt;DocumentType&lt;/code&gt;, etc.&lt;/li&gt;
&lt;li&gt;&lt;code&gt;AnyItemTest&lt;/code&gt; → &lt;code&gt;AnyItemType&lt;/code&gt; (analogous to &lt;code&gt;AnyMapType&lt;/code&gt; etc.)&lt;/li&gt;
&lt;li&gt;&lt;code&gt;AnyNodeKindTest&lt;/code&gt; → &lt;code&gt;AnyNodeType&lt;/code&gt;&lt;/li&gt;
&lt;li&gt;&lt;code&gt;NamespaceNodeTest&lt;/code&gt; → &lt;code&gt;NamespaceType&lt;/code&gt; (in analogy with the rules for documents, which does not contain &lt;code&gt;Node&lt;/code&gt;)&lt;/li&gt;
&lt;li&gt;Basically, all &lt;code&gt;RegularItemType&lt;/code&gt; and &lt;code&gt;XNodeType&lt;/code&gt; RHS rules should probably end with &lt;code&gt;Type&lt;/code&gt;.&lt;/li&gt;
&lt;/ul&gt;
&lt;p&gt;If we prefer the &lt;code&gt;Test&lt;/code&gt; naming scheme, we should rename &lt;code&gt;JNodeType&lt;/code&gt; to &lt;code&gt;JNodeTest&lt;/code&gt;, etc.&lt;/p&gt;
&lt;/div&gt;&lt;/div&gt;</description>
</item>
