<item>
   <title>Issue #44 created</title>
   <pubDate>2021-01-06T17:35:41Z</pubDate>
   <link>https://github.com/qt4cg/qtspecs/issues/44</link>
   <guid>https://qt4cg.org/@qt4cg/2021/#created-44</guid>
   <description>&lt;div&gt;&lt;p&gt;[XPath] [XQuery] Support RecordTest self references without occurrence indicators&lt;/p&gt;&lt;div class="markup"&gt;&lt;p&gt;This would be useful for defining things like binary trees, where the fields are optional but (if supplied) the values are not. So it is more logical to define them as:&lt;/p&gt;
&lt;pre&gt;&lt;code&gt;declare item-type binary-tree as record(
    left? as ..,
    right? as ..,
    value as item()*
);
&lt;/code&gt;&lt;/pre&gt;
&lt;/div&gt;&lt;/div&gt;</description>
</item>
