<item>
   <title>Pull request #223 created</title>
   <pubDate>2022-10-27T15:59:51Z</pubDate>
   <link>https://github.com/qt4cg/qtspecs/pull/223</link>
   <guid>https://qt4cg.org/@qt4cg/2022/#created-223</guid>
   <description>&lt;div&gt;&lt;p&gt;Allow eg in fos:expression and fos:result&lt;/p&gt;&lt;div class="markup"&gt;&lt;p&gt;This PR formats &lt;code&gt;eg&lt;/code&gt; in &lt;code&gt;fos:expression&lt;/code&gt; and &lt;code&gt;fos:result&lt;/code&gt; as a block. I don't think this will have any detrimental effects as it's done during the "merging" process.&lt;/p&gt;
&lt;/div&gt;&lt;/div&gt;</description>
</item>
