<item>
   <title>Issue #1902 created</title>
   <pubDate>2025-03-27T10:20:49Z</pubDate>
   <link>https://github.com/qt4cg/qtspecs/issues/1902</link>
   <guid>https://qt4cg.org/@qt4cg/2025/#created-1902</guid>
   <description>&lt;div&gt;&lt;p&gt;`binary:unpack-integer`, overflow/underflow&lt;/p&gt;&lt;div class="markup"&gt;&lt;p&gt;If &lt;code&gt;binary:unpack-integer&lt;/code&gt; or &lt;code&gt;binary:unpack-unsigned-integer&lt;/code&gt; generates a value that exceeds the range supported by the implementation, &lt;code&gt;err:FOAR0002&lt;/code&gt; should be raised.&lt;/p&gt;
&lt;p&gt;Related: https://github.com/expath/expath-cg/issues/116&lt;/p&gt;
&lt;/div&gt;&lt;/div&gt;</description>
</item>
