<item>
   <title>Pull request #2289 created</title>
   <pubDate>2025-11-13T16:56:18Z</pubDate>
   <link>https://github.com/qt4cg/qtspecs/pull/2289</link>
   <guid>https://qt4cg.org/@qt4cg/2025/#created-2289</guid>
   <description>&lt;div&gt;&lt;p&gt;2195 (partial) Editorial notes (incremental)&lt;/p&gt;&lt;div class="markup"&gt;&lt;p&gt;This PR contains some more editorial changes. Notes:&lt;/p&gt;
&lt;ul&gt;
&lt;li&gt;I have revised the »Summary of Changes« to (hopefully) make it more clear which »arrows« the description refers to, and I have updated the icons.&lt;/li&gt;
&lt;li&gt;I have corrected some code equivalencies in the Binary Module. The &lt;code&gt;bin:shift&lt;/code&gt; equivalency (possibly others) still needs to be fixed).&lt;/li&gt;
&lt;/ul&gt;
&lt;/div&gt;&lt;/div&gt;</description>
</item>
